{"cameraMode":{"drawMode":0,"name":"Shaded","section":"Shading Mode"},"sceneLighting":false,"audioPlay":false,"sceneViewState":{"m_AlwaysRefresh":false,"showFog":true,"showSkybox":false,"showFlares":true,"showImageEffects":true,"showParticleSystems":true,"showVisualEffectGraphs":true,"m_FxEnabled":true},"in2DMode":false,"pivot":{"x":-2.56935453414917,"y":-0.4091021418571472,"z":1.0102734565734864},"rotation":{"x":0.2296166718006134,"y":-0.6671488881111145,"z":0.22832803428173066,"w":0.6710560321807861},"size":4.284278869628906,"orthographic":false}